{
  "report_version": "1.0",
  "generated_utc": "2026-05-28T14:44:20Z",
  "iteration": "stage_b_llama31_8b_base_v1_i10r_counterbalanced",
  "status": "completed",
  "operation_mode": "additions_only",
  "expected_total_additions": 16,
  "actual_total_additions": 16,
  "additions_exact_match": true,
  "parent_counts": {
    "train_rows": 1969,
    "val_rows": 233
  },
  "revised_counts": {
    "train_rows": 1982,
    "val_rows": 236
  },
  "existing_rows_changed": {
    "train_changed_count": 0,
    "val_changed_count": 0,
    "train_changed_row_indices_sample": [],
    "val_changed_row_indices_sample": [],
    "pass": true
  },
  "additions_breakdown": {
    "train_additions": 13,
    "val_additions": 3,
    "block_distribution": {
      "nocall_contrastive_pair_block_v2": 10,
      "read_file_symbol_name_commitment_counterbalance_v1": 6
    },
    "tool_distribution": {
      "no_tool": 5,
      "read_file": 6,
      "rg_search": 5
    },
    "family_distribution": {
      "malformed_regex_underspecified_search_adversarial_boundary": 10,
      "read_file_symbol_name_commitment_instability": 6
    }
  },
  "localization_checks": {
    "all_rows_localized_family": true,
    "localized_family_expected": [
      "malformed_regex_underspecified_search_adversarial_boundary",
      "read_file_symbol_name_commitment_instability"
    ],
    "pass": true
  },
  "contrastive_pair_validation": {
    "expected_pair_count": 5,
    "pair_count": 5,
    "all_pairs_pass": true,
    "pairs": [
      {
        "pair_id": "pair_01",
        "rows": 2,
        "bad_rows": 1,
        "good_rows": 1,
        "semantic_token_consistent": true,
        "path_consistent": true,
        "pass": true
      },
      {
        "pair_id": "pair_02",
        "rows": 2,
        "bad_rows": 1,
        "good_rows": 1,
        "semantic_token_consistent": true,
        "path_consistent": true,
        "pass": true
      },
      {
        "pair_id": "pair_03",
        "rows": 2,
        "bad_rows": 1,
        "good_rows": 1,
        "semantic_token_consistent": true,
        "path_consistent": true,
        "pass": true
      },
      {
        "pair_id": "pair_04",
        "rows": 2,
        "bad_rows": 1,
        "good_rows": 1,
        "semantic_token_consistent": true,
        "path_consistent": true,
        "pass": true
      },
      {
        "pair_id": "pair_05",
        "rows": 2,
        "bad_rows": 1,
        "good_rows": 1,
        "semantic_token_consistent": true,
        "path_consistent": true,
        "pass": true
      }
    ]
  },
  "counterbalanced_block_validation": {
    "expected_nocall_contrastive_rows": 10,
    "actual_nocall_contrastive_rows": 10,
    "expected_read_file_symbol_rows": 6,
    "actual_read_file_symbol_rows": 6,
    "read_file_path_forms": {
      "mnt": 3,
      "opt": 3
    },
    "read_file_style_variants": {
      "exact_envelope": 4,
      "paraphrastic_envelope": 2
    },
    "read_file_line_window_pass": true,
    "pass": true
  },
  "uncertainty_conditioning_validation": {
    "expected_rows": 0,
    "actual_rows": 0,
    "pass": true
  },
  "approval_state": {
    "approved_to_generate_dataset": false,
    "approved_to_run": false,
    "approved_to_train": false,
    "approved_to_promote": false
  }
}
